xbps/__init__.py
xbps/py.typed
xbps/scripts/xstage.py
xbps/util/__init__.py
xbps-0.0.1.dist-info/licenses/LICENSE
xbps-0.0.1.dist-info/METADATA
xbps-0.0.1.dist-info/WHEEL
xbps-0.0.1.dist-info/entry_points.txt
xbps-0.0.1.dist-info/top_level.txt
xbps-0.0.1.dist-info/RECORD
